{
  "parent": "minecraft:recipes/root",
  "criteria": {
    "has_levitation_orb": {
      "conditions": {
        "items": [
          {
            "items": "ethermist:levitation_orb"
          }
        ]
      },
      "trigger": "minecraft:inventory_changed"
    },
    "has_the_recipe": {
      "conditions": {
        "recipe": "ethermist:wooden_levitation_wand_from_wooden_wither_wand_and_levitation_orb"
      },
      "trigger": "minecraft:recipe_unlocked"
    }
  },
  "requirements": [
    [
      "has_the_recipe",
      "has_levitation_orb"
    ]
  ],
  "rewards": {
    "recipes": [
      "ethermist:wooden_levitation_wand_from_wooden_wither_wand_and_levitation_orb"
    ]
  }
}